.DS_Store
pydeck/.DS_Store
pydeck/__init__.py
pydeck/_version.py
pydeck/frontend_semver.py
pydeck/settings.py
pydeck/bindings/__init__.py
pydeck/bindings/base_map_provider.py
pydeck/bindings/deck.py
pydeck/bindings/json_tools.py
pydeck/bindings/layer.py
pydeck/bindings/light_settings.py
pydeck/bindings/map_styles.py
pydeck/bindings/view.py
pydeck/bindings/view_state.py
pydeck/data_utils/__init__.py
pydeck/data_utils/binary_transfer.py
pydeck/data_utils/color_scales.py
pydeck/data_utils/type_checking.py
pydeck/data_utils/viewport_helpers.py
pydeck/exceptions/__init__.py
pydeck/exceptions/exceptions.py
pydeck/io/.DS_Store
pydeck/io/__init__.py
pydeck/io/html.py
pydeck/io/templates/index.j2
pydeck/io/templates/style.j2
pydeck/nbextension/.DS_Store
pydeck/nbextension/__init__.py
pydeck/nbextension/static/.DS_Store
pydeck/nbextension/static/.gitkeep
pydeck/nbextension/static/extensionRequires.js
pydeck/nbextension/static/index.js
pydeck/nbextension/static/index.js.map
pydeck/types/__init__.py
pydeck/types/base.py
pydeck/types/function.py
pydeck/types/image.py
pydeck/types/string.py
pydeck/widget/__init__.py
pydeck/widget/_frontend.py
pydeck/widget/debounce.py
pydeck/widget/widget.py
pydeck-0.9.0.data/data/etc/jupyter/nbconfig/notebook.d/pydeck.json
pydeck-0.9.0.data/data/share/jupyter/nbextensions/pydeck/extensionRequires.js
pydeck-0.9.0.data/data/share/jupyter/nbextensions/pydeck/index.js
pydeck-0.9.0.data/data/share/jupyter/nbextensions/pydeck/index.js.map
pydeck-0.9.0.dist-info/LICENSE.txt
pydeck-0.9.0.dist-info/METADATA
pydeck-0.9.0.dist-info/WHEEL
pydeck-0.9.0.dist-info/top_level.txt
pydeck-0.9.0.dist-info/RECORD
