Metadata-Version: 2.1
Name: pydeck
Version: 0.9.0
Summary: Widget for deck.gl maps
Home-page: https://github.com/visgl/deck.gl/tree/master/bindings/pydeck
Author: Andrew Duberstein
Author-email: ajduberstein@gmail.com
License: Apache License 2.0
Keywords: data,visualization,graphics,GIS,maps
Classifier: Intended Audience :: Developers
Classifier: Intended Audience :: Science/Research
Classifier: Topic :: Multimedia :: Graphics
Classifier: Programming Language :: Python :: 3
Classifier: Programming Language :: Python :: 3.8
Classifier: Programming Language :: Python :: 3.9
Classifier: Programming Language :: Python :: 3.10
Classifier: Programming Language :: Python :: 3.11
Classifier: Programming Language :: Python :: 3.12
Classifier: Programming Language :: Python :: 3.13
Classifier: Framework :: Jupyter
Requires-Python: >=3.8
Provides-Extra: carto
Provides-Extra: jupyter
License-File: LICENSE.txt
